{"dct_title_s": "Airports Portland Metro, Oregon 1996","dct_description_sm": ["This polygon data layer represents airports for Portland Metro, Oregon in 1996. The dataset was originally published by the Metro Data Resource Center in February 2001."],"dct_language_sm": ["eng"],"dct_creator_sm": ["Metro Data Resource Center"],"schema_provider_s": "American Geographical Society Library – UWM Libraries","gbl_resourceClass_sm": ["Datasets"],"gbl_resourceType_sm": ["Polygon data"],"dcat_theme_sm": ["Transportation"],"dct_temporal_sm": ["1996"],"dct_issued_s": "2001","gbl_indexYear_im": [1996],"dct_spatial_sm": ["Portland Metro","Oregon"],"locn_geometry": "ENVELOPE(-122.388704, -122.962482, 45.600826, 45.532886)","dcat_bbox": "ENVELOPE(-122.962482, -122.388704, 45.600826, 45.532886)","dct_rights_sm": ["<a href=\"https://uwm.edu/libraries/digital-collections/copyright-digcoll/\">Please see the UWM Libraries statement on Copyright and Digital Collections</a>.","Although this data is being distributed by the American Geographical Society Library at the University of Wisconsin-Milwaukee Libraries, no warranty expressed or implied is made by the University as to the accuracy of the data and related materials. The act of distribution shall not constitute any such warranty, and no responsibility is assumed by the University in the use of this data, or related materials."],"dct_accessRights_s": "Public","dct_format_s": "Shapefile","dct_references_s": "{\"http://schema.org/url\":\"https://geodiscovery.uwm.edu/catalog/ark:-77981-gmgsvm42x06\",\"http://schema.org/downloadUrl\":\"https://geodata.uwm.edu/public/gmgsvm42x06/PortlandMetro_Airports_1996.zip\",\"http://www.isotc211.org/schemas/2005/gmd\":\"https://raw.githubusercontent.com/OpenGeoMetadata/edu.uwm/main/metadata-iso/gmgsvm42x06_ISO.xml\"}","id": "ark:-77981-gmgsvm42x06","dct_identifier_sm": ["ark:/77981/gmgsvm42x06"],"gbl_mdModified_dt": "2023-10-25T19:58:43.5295023Z","gbl_mdVersion_s": "Aardvark","gbl_suppressed_b": false}